{
    "Watershed code": "91-3275",
    "Gazetted name": "KIMSQUIT RIVER",
    "Flows Into": "HEAD OF DEAN CHANNEL",
    "Year": "1992",
    "District No.": "7",
    "Statistical Area": "8",
    "Subdistrict No.": "8",
    "Subdistrict Name": "BELLA COOLA",
    "(A) Enhancement or intense biological activities": "unselected",
    "(B) Unusual mortalities": "unselected",
    "(C) Obstruction or changes in habitat with recommendations": "unselected",
    "(D) Large variations in sex ratio or unusual number of jacks": "unselected",
    "(E) Unusual high or low water flow level during spawning period": "selected",
    "Additional (A) Evidence of erosion and silting": "CONSTANT COURSE CHANGES AND BANK EROSION.",
    "Additional (B) Particulars of scouring of spawning beds": "UNKNOWN",
    "Additional (C) Water levels flow": "HIGH OCT. 23",
    "Biological (D) Particulars of distribution": "SK. IN LAKE & UPPER TRIBS. PK. & CM. IN SIDE CHANNELS & MAINSTEM. CO. & CK. THROUGHOUT TO LAKE",
    "Biological (E) Comments on predators": "HIGH BY BEARS AND SEALS",
    "Biological (F) Evidence of digging eggs": "NIL",
    "Dates of inspection (1)": "1-2 TIMES WEEK",
    "Date of inspection": null,
    "Spawning run timing and estimated number": {},
    "Comments (K)": null,
    "Second local name": null,
    "Biological (G) New obstruction": null,
    "First local name": null
}