{
    "Year": "1995",
    "Gazetted name": "ENGLISHMAN RIVER",
    "RAB code": "92-3800",
    "Area": "14-5",
    "District": "03",
    "Sub": "14S Qualicum Beach",
    "Flows into": "GEORGIA STRAIT",
    "Latitude": "49 19 47",
    "Longitude": "124 17 36",
    "Field Crew": "Eli Rosengard",
    "Inspection dates": "Aug 15 Oct 05 Oct 15 Oct 27 Nov 04 Nov 22 Nov 24 Dec 06",
    "(5) Escapement comments": "unselected",
    "(6) General comments": "unselected",
    "(7) Enhancement": "unselected",
    "(8) Unusual mortalities": "unselected",
    "(9) Upslope instability": "unselected",
    "(10) Debris jams present": "unselected",
    "(11) Severe bank erosion": "selected",
    "(13) Unusual drought": "unselected",
    "(14) Flood": "selected",
    "(15) General comments": "selected",
    "(16) Fish access": "unselected",
    "(17) Spawning site": "selected",
    "(18) Augementation": "unselected",
    "(19) Other": "unselected",
    "Biological details particulars": "Normal. Difficult to evaluate due to high water.",
    "Present SK": "unselected",
    "Present CO": "unselected",
    "Present PK": "unselected",
    "Present CM": "unselected",
    "Present CN": "unselected",
    "Study SK": "unselected",
    "Study CO": "unselected",
    "Study PK": "unselected",
    "Study CM": "unselected",
    "Study CN": "unselected",
    "Predators": "unselected",
    "(20) General comments": "unselected",
    "(21) General comments not covered": "unselected",
    "(22) Supplementary documentation": "unselected",
    "Comments on condition": "(1) Other methods for CO Run 1: Spot check (1) Other methods for PK Run 1: Spot check (1) Other methods for CM Run 1: Spot check (1) Other methods for CN Run 1: Spot check (11) Bank erosion: Bank erosion noted. Spawning channel intake plugged after flood. (17) Spawning site recommendations: Course of stream shifted near M&B channel Extensive flood in mid November caused scouring. (14) Flood: More flow than normal in late summer. Near record rain in November hampers stream evaluations. (15) General Comments on Unusual Conditions: Some of early spawn probably lost due to flooding. High water made capture of brood stock difficult.",
    "Person preparing report": "Eli Rosengard / Patrolman",
    "Bio Sampling": null,
    "Details affecting salmon escapement": {
        "SK 1": {
            "Methods": "1",
            "%Spawn habitat surveyed": "0",
            "Rel": "1",
            "Enum Class": "0",
            "Esc Code": "N.O."
        },
        "SK 2": {
            "%Spawn habitat surveyed": "0",
            "Enum Class": "0",
            "Esc Code": "N.O."
        },
        "CO 1": {
            "Methods": "1,10",
            "%Spawn habitat surveyed": "0",
            "Rel": "2",
            "Enum Class": "0",
            "Esc Code": "A.C.",
            "Est total adults": "400"
        },
        "CO 2": {
            "%Spawn habitat surveyed": "0",
            "Enum Class": "0",
            "Esc Code": "N.O."
        },
        "PK 1": {
            "Methods": "1,10",
            "%Spawn habitat surveyed": "0",
            "Rel": "2",
            "Enum Class": "0",
            "Esc Code": "A.C.",
            "Est total adults": "50"
        },
        "PK 2": {
            "%Spawn habitat surveyed": "0",
            "Enum Class": "0",
            "Esc Code": "N.O."
        },
        "CM 1": {
            "Methods": "1,10",
            "%Spawn habitat surveyed": "0",
            "Rel": "4",
            "Enum Class": "0",
            "Esc Code": "A.C.",
            "Est total adults": "2,000"
        },
        "CM 2": {
            "%Spawn habitat surveyed": "0",
            "Enum Class": "0",
            "Esc Code": "N.O."
        },
        "CN 1": {
            "Methods": "1,10",
            "%Spawn habitat surveyed": "0",
            "Rel": "3",
            "Enum Class": "0",
            "Esc Code": "A.C.",
            "Est total adults": "40"
        },
        "CN 2": {
            "%Spawn habitat surveyed": "0",
            "Enum Class": "0",
            "Esc Code": "N.O."
        },
        "ST 1": {
            "%Spawn habitat surveyed": "0",
            "Enum Class": "0",
            "Esc Code": "N.O."
        },
        "ST 2": {
            "%Spawn habitat surveyed": "0",
            "Enum Class": "0",
            "Esc Code": "N.O."
        },
        "AT 1": {
            "%Spawn habitat surveyed": "0",
            "Enum Class": "0",
            "Esc Code": "N.O."
        },
        "AT 2": {
            "%Spawn habitat surveyed": "0",
            "Enum Class": "0",
            "Esc Code": "N.O."
        },
        "CT 1": {
            "%Spawn habitat surveyed": "0",
            "Enum Class": "0",
            "Esc Code": "N.I."
        },
        "CT 2": {
            "%Spawn habitat surveyed": "0",
            "Enum Class": "0",
            "Esc Code": "N.I."
        },
        "TR 1": {
            "%Spawn habitat surveyed": "0",
            "Enum Class": "0",
            "Esc Code": "N.I."
        },
        "TR 2": {
            "%Spawn habitat surveyed": "0",
            "Enum Class": "0",
            "Esc Code": "N.I."
        }
    },
    "Spawning run timing": {
        "CO 1": {
            "Arrival month": "Oct",
            "Start month": "Oct",
            "Start day": "11-20",
            "Peak month": "Nov",
            "Peak day": "11-20",
            "End month": "Dec",
            "End day": "21-31"
        },
        "PK 1": {
            "Arrival month": "Aug",
            "Arrival day": "11-20",
            "Start month": "Sep",
            "Start day": "1-10",
            "Peak month": "Sep",
            "Peak day": "21-31",
            "End month": "Oct",
            "End day": "1-10"
        },
        "CM 1": {
            "Arrival month": "Oct",
            "Arrival day": "11-20",
            "Start month": "Oct",
            "Start day": "21-31",
            "Peak month": "Nov",
            "Peak day": "1-10",
            "End month": "Nov",
            "End day": "21-31"
        },
        "CN 1": {
            "Arrival month": "Aug",
            "Arrival day": "21-31"
        }
    },
    "Second local name": null,
    "First local name": null,
    "End date": null,
    "Start date": null
}