{
    "Year": "1997",
    "Gazetted name": "TSOLUM RIVER",
    "RAB code": "92-2800-010",
    "Area": "14-1",
    "District": "03",
    "Sub": "14N Comox",
    "Flows into": "COURTENAY RIVER-COMOX HARBOUR",
    "Latitude": "49 41 43",
    "Longitude": "124 59 40",
    "Field Crew": "Eli Rosengard",
    "(5) Escapement comments": "selected",
    "(6) General comments": "selected",
    "(7) Enhancement": "selected",
    "(8) Unusual mortalities": "unselected",
    "(9) Upslope instability": "unselected",
    "(10) Debris jams present": "unselected",
    "(11) Severe bank erosion": "selected",
    "(13) Unusual drought": "unselected",
    "(14) Flood": "selected",
    "(15) General comments": "unselected",
    "(16) Fish access": "unselected",
    "(17) Spawning site": "unselected",
    "(18) Augementation": "unselected",
    "(19) Other": "unselected",
    "Biological details particulars": "Normal except as noted with regard to chum.",
    "Present SK": "unselected",
    "Present CO": "unselected",
    "Present PK": "unselected",
    "Present CM": "unselected",
    "Present CN": "unselected",
    "Study SK": "unselected",
    "Study CO": "unselected",
    "Study PK": "unselected",
    "Study CM": "unselected",
    "Study CN": "unselected",
    "Predators": "unselected",
    "(20) General comments": "selected",
    "(21) General comments not covered": "unselected",
    "(22) Supplementary documentation": "selected",
    "Comments on condition": "(4) Describe basis for estimating total adults CO Run 1: presence noted. (4) Describe basis for estimating total adults CM Run 1: 3500 trucked from Puntledge 2000 natural spawning. (5) General Comments on Escapement Estimation: Impossible to assess coho without multiple swimmers. Difficult to do chum numbers because trucked fish didn't align as normal. (6) General Comments on Run Timing: difficult to establish run timing on pinks due to high water. (7) Enhancements: Ongoing studies by Tsolum River Task Force and streamkeepers groups. (14) Flood: Severe flooding in March 1997 and also early October. (11) Bank erosion: River changed course and went through Ser Van Te Farm on Dove Creek Road. (20) On Predator Interactions: River and estuary seal predation as Puntledge system. DFO begins cull of riverine seals. (22) List Supplementary Documentation: Much study has been done of this system in recent years because of the acid mine drainage problem and Inland Highway alignment. Detailed inventory and mapping work carried out. Low summer flow problem looked at as a component of the problem. New system for dealing with mine being looked at for funding. Highway design through Oxbow raises concerns through community.",
    "Person preparing report": "Eli Rosengard / Patrolman",
    "Bio Sampling": null,
    "Details affecting salmon escapement": {
        "SK 1": {
            "%Spawn habitat surveyed": "0",
            "Enum Class": "0",
            "Esc Code": "N.O."
        },
        "SK 2": {
            "%Spawn habitat surveyed": "0",
            "Enum Class": "0",
            "Esc Code": "N.O."
        },
        "CO 1": {
            "Methods": "1",
            "%Spawn habitat surveyed": "5",
            "Rel": "1",
            "Enum Class": "4",
            "Esc Code": "A.C.",
            "Est total adults": "1"
        },
        "CO 2": {
            "%Spawn habitat surveyed": "0",
            "Enum Class": "0",
            "Esc Code": "N.O."
        },
        "PK 1": {
            "Methods": "1,2",
            "N": "2",
            "%Spawn habitat surveyed": "30",
            "Rel": "2",
            "Enum Class": "3",
            "Esc Code": "A.C.",
            "Est total adults": "200"
        },
        "PK 2": {
            "%Spawn habitat surveyed": "0",
            "Enum Class": "0",
            "Esc Code": "N.O."
        },
        "CM 1": {
            "Methods": "2",
            "N": "3",
            "%Spawn habitat surveyed": "65",
            "Rel": "3",
            "Enum Class": "3",
            "Esc Code": "A.C.",
            "Est total adults": "5,500"
        },
        "CM 2": {
            "%Spawn habitat surveyed": "0",
            "Enum Class": "0",
            "Esc Code": "N.O."
        },
        "CN 1": {
            "%Spawn habitat surveyed": "0",
            "Enum Class": "0",
            "Esc Code": "N.O."
        },
        "CN 2": {
            "%Spawn habitat surveyed": "0",
            "Enum Class": "0",
            "Esc Code": "N.O."
        },
        "ST 1": {
            "%Spawn habitat surveyed": "0",
            "Enum Class": "0",
            "Esc Code": "N.O."
        },
        "ST 2": {
            "%Spawn habitat surveyed": "0",
            "Enum Class": "0",
            "Esc Code": "N.O."
        },
        "AT 1": {
            "%Spawn habitat surveyed": "0",
            "Enum Class": "0",
            "Esc Code": "N.O."
        },
        "AT 2": {
            "%Spawn habitat surveyed": "0",
            "Enum Class": "0",
            "Esc Code": "N.O."
        },
        "CT 1": {
            "%Spawn habitat surveyed": "0",
            "Enum Class": "0",
            "Esc Code": "N.I."
        },
        "CT 2": {
            "%Spawn habitat surveyed": "0",
            "Enum Class": "0",
            "Esc Code": "N.I."
        },
        "TR 1": {
            "%Spawn habitat surveyed": "0",
            "Enum Class": "0",
            "Esc Code": "N.I."
        },
        "TR 2": {
            "%Spawn habitat surveyed": "0",
            "Enum Class": "0",
            "Esc Code": "N.I."
        }
    },
    "Spawning run timing": {
        "PK 1": {
            "Arrival month": "Sep",
            "Arrival day": "11-20",
            "Start month": "Sep",
            "Start day": "21-31",
            "Peak month": "Oct",
            "Peak day": "1-10",
            "End month": "Oct",
            "End day": "11-20"
        },
        "CM 1": {
            "Arrival month": "Oct",
            "Arrival day": "21-31",
            "Start month": "Nov",
            "Start day": "1-10",
            "Peak month": "Nov",
            "Peak day": "11-20",
            "End month": "Nov",
            "End day": "21-31"
        }
    },
    "End date": null,
    "First local name": null,
    "Second local name": null,
    "Inspection dates": null,
    "Start date": null
}